{
	"list": [
		{
			"name": "单TNT轰炸机普通版",
			"bv": "BV1hT4y1m7rY",
			"date": "2022-01-14",
			"type": "3-way",
			"extension": "zip"
		},
		{
			"name": "双TNT三向轰炸机",
			"bv": "BV15Y4y1Y7TE",
			"date": "2022-04-22",
			"type": "3-way",
			"extension": "rar"
		},
		{
			"name": "双TNT自返回三向轰炸机",
			"bv": "BV1w5411d7Fu",
			"date": "2022-05-06",
			"type": "3-way",
			"extension": "rar"
		},
		{
			"name": "单TNT轰炸机更好的开关",
			"bv": "BV1Qg4y1y7Md",
			"date": "2023-12-15",
			"type": "3-way",
			"extension": "zip"
		},
		{
			"name": "三倍火力三向轰炸机",
			"bv": "BV1C14y1b7mf",
			"date": "2022-08-12",
			"type": "3-way",
			"extension": "zip"
		},
		{
			"name": "无预留三向轰炸机",
			"bv": "BV1xo4y167C2",
			"date": "2023-03-10",
			"type": "3-way",
			"extension": "zip"
		},
		{
			"name": "仅29个方块的极简双向复制三向轰炸机",
			"bv": "BV1uJ4m1x75U",
			"date": "2024-02-09",
			"type": "3-way",
			"extension": "zip"
		},
		{
			"name": "1.7、3.3、6.7倍速三向轰炸机",
			"bv": "BV1Ew411j71G",
			"date": "2024-01-26",
			"type": "3-way",
			"extension": "zip"
		},
		{
			"name": "1.111倍速下弹加速三向轰炸机",
			"bv": "BV1y2421w7ga",
			"date": "2024-02-02",
			"type": "3-way",
			"extension": "zip"
		},
		{
			"name": "无安全连杆版无沟世吞",
			"bv": "BV11h4y1t7Mh",
			"date": "2023-05-20",
			"type": "eater",
			"extension": "zip"
		},
		{
			"name": "9宽下降沟世界吞噬者",
			"bv": "BV1s64y1L7YZ",
			"date": "2023-12-01",
			"type": "eater",
			"extension": "txt"
		},
		{
			"name": "无沟世吞V2",
			"bv": "BV1rP4y1r75J",
			"date": "2023-01-21",
			"type": "eater",
			"extension": "txt"
		},
		{
			"name": "无沟世吞V3",
			"bv": "BV1za4y1P7cw",
			"date": "2023-04-22",
			"type": "eater",
			"extension": "zip"
		},
		{
			"name": "14高无沟地吞",
			"bv": "BV1wy4y197gs",
			"date": "2023-02-03",
			"type": "eater",
			"extension": "txt"
		},
		{
			"name": "16高无沟地吞",
			"bv": "BV1XW4y137fh",
			"date": "2023-01-14",
			"type": "eater",
			"extension": "txt"
		},
		{
			"name": "无侧沟（防爆沟）世吞",
			"bv": "BV18m4y1E7P7",
			"date": "2023-07-12",
			"type": "eater",
			"extension": "txt"
		},
		{
			"name": "10高地吞",
			"bv": "BV1Cu41197MA",
			"date": "2022-02-11",
			"type": "eater",
			"extension": "zip"
		},
		{
			"name": "13高低卡顿地吞",
			"bv": "BV1Nr4y1o7kv",
			"date": "2023-08-19",
			"type": "eater",
			"extension": "zip"
		},
		{
			"name": "主世界全自动3宽挖沟机",
			"bv": "BV1jW4y1w7jy",
			"date": "2024-01-19",
			"type": "gap",
			"extension": "zip"
		},
		{
			"name": "地狱全自动3宽挖沟机",
			"bv": "BV1564y1W7yS",
			"date": "2023-12-22",
			"type": "gap",
			"extension": "txt"
		},
		{
			"name": "无预留密集TNT推土机",
			"bv": "BV1mG411L7Fm",
			"date": "2022-10-28",
			"type": "others",
			"extension": "zip"
		},
		{
			"name": "2gt铺活塞机",
			"bv": "BV1HL4y1z744",
			"date": "2021-10-01",
			"type": "block",
			"extension": "zip"
		},
		{
			"name": "4gt铺天花板机",
			"bv": "BV12V4y1h7XR",
			"date": "2023-06-30",
			"type": "block",
			"extension": "zip"
		},
		{
			"name": "5倍速铺沙机",
			"bv": "BV17S4y1u7Vx",
			"date": "2022-03-18",
			"type": "block",
			"extension": "zip"
		},
		{
			"name": "4倍速铺铁砧机",
			"bv": "BV1534y1t7XE",
			"date": "2022-03-18",
			"type": "block",
			"extension": "zip"
		},
		{
			"name": "7x2单发盾构",
			"bv": "BV18S4y127XZ",
			"date": "2022-04-09",
			"type": "tunnel",
			"extension": "zip"
		},
		{
			"name": "5x3单发盾构",
			"bv": "BV1bL411f7J9",
			"date": "2023-04-14",
			"type": "tunnel",
			"extension": "zip"
		},
		{
			"name": "5x3 二、三连发盾构机",
			"bv": "BV1NT411V7Vx",
			"date": "2022-06-24",
			"type": "tunnel",
			"extension": "zip"
		},
		{
			"name": "12倍速排水机",
			"bv": "BV1db4y1K7BB",
			"date": "2023-12-08",
			"type": "water",
			"extension": "zip"
		},
		{
			"name": "垂直复制采矿机",
			"bv":"BV1fh4y197n1",
			"date": "2023-06-10",
			"type": "quarry",
			"extension": "zip"
		},
		{
			"name": "主世界超快采矿机",
			"bv": "BV1Mi4y1i7y5",
			"date": "2024-01-12",
			"type": "quarry",
			"extension": "txt"
		},
		{
			"name": "超快末地石采矿机",
			"bv": "BV1qQ4y1L7vv",
			"date": "2024-01-05",
			"type": "quarry",
			"extension": "zip"
		},
		{
			"name": "地狱采矿机（破基岩版）",
			"bv": "BV11x42117Uq",
			"date": "2024-03-01",
			"type": "quarry",
			"extension": "txt"
		},
		{
			"name": "地狱采矿机",
			"bv": "BV1Sr421H7yg",
			"date": "2024-03-15",
			"type": "quarry",
			"extension": "txt"
		},
		{
			"name": "三向破基岩V4",
			"bv": "BV18q4y1B781",
			"date": "2021-12-17",
			"type": "bedrock",
			"extension": "zip"
		},
		{
			"name": "三向破基岩V1",
			"bv": "BV1gP4y1Y7hR",
			"date": "2021-09-10",
			"type": "bedrock",
			"extension": "zip"
		},
		{
			"name": "三向破基岩V2",
			"bv": "BV1wb4y117sn",
			"date": "2021-09-24",
			"type": "bedrock",
			"extension": "zip"
		},
		{
			"name": "三向破基岩V3",
			"bv": "BV1844y1x7Ai",
			"date": "2021-10-15",
			"type": "bedrock",
			"extension": "zip"
		},
		{
			"name": "掏空末地5件套",
			"bv": "BV1tK4y1G7mh",
			"date": "2021-05-21",
			"type": "others",
			"extension": "zip"
		}
	]
}
